{
  "id": "w_83bfea58b33d",
  "ru": "какой местоим.",
  "pos": "ма (определит.,перед определяемым словом) какая красота! ма хоза да!",
  "senses": [
    {
      "ing": "мишта (вопр.) *фу (вопр.) *малагIа (вопр.) *цхьаккха а (какой-нибудь, неопр.) нет ли у вас какого вопроса? цхьаккха а хаттар дий шун?",
      "definition": null,
      "examples": [
        {
          "ing": "",
          "ru": "",
          "audio": null
        }
      ]
    }
  ],
  "audio": {
    "word": null
  },
  "source": "rusing"
}